LICENSES.txt
MANIFEST.in
README.md
REQUIREMENTS.txt
setup.cfg
setup.py
CramUnit.egg-info/PKG-INFO
CramUnit.egg-info/SOURCES.txt
CramUnit.egg-info/dependency_links.txt
CramUnit.egg-info/requires.txt
CramUnit.egg-info/top_level.txt
bin/run_cram_unit.py
cram_unit/__init__.py
cram_unit/crammer.py
cram_unit/io.py