Metadata-Version: 1.1
Name: CramUnit
Version: 0.7
Summary: Tool to create Unittests/Xunit output from cram (*.t) tests.
Home-page: http://github.com/mpkocher/CramUnit
Author: mpkocher
Author-email: mkocher@pacificbiosciences.com
License: BSD
Download-URL: https://github.com/mpkocher/CramUnit/tarball/0.7
Keywords: testing,cram,jenkins,xunit
Platform: UNKNOWN
Classifier: Development Status :: 4 - Beta
Classifier: Environment :: Console
Classifier: Topic :: Software Development :: Bug Tracking
